Metadata-Version: 2.1
Name: dsp-py
Version: 1.0
Summary: A support library for Digital Signal Processing
Home-page: https://github.com/dinhanhx/DSP-py-lib
Author: dinhanhx
Author-email: dinhanhx@gmail.com
License: The Unlicensed
Platform: UNKNOWN
